[
 {
    "Mode": "Swap",
    "Takes": {
		"Code": "game:food-bowl-large-blue-raw-meat",
        "Type": "Block",        
		"Remove": true	
    },
    "Tool": {
        "Code": "game:salt",
        "Type": "item",
		"StackSize": 32
    },
    "Makes": [{
        "Code": "game:food-bowl-large-blue-salted-meat",
        "Type": "Block",
        "StackSize": 1
    }],
    "IsTool": false,
    "CraftSound": "sounds/block/planks",
    "Disabled": false
 },
 {
    "Mode": "Swap",
    "Takes": {
		"Code": "game:food-bowl-large-brown-raw-meat",
        "Type": "Block",        
		"Remove": true	
    },
    "Tool": {
        "Code": "game:salt",
        "Type": "item",
		"StackSize": 32
    },
    "Makes": [{
        "Code": "game:food-bowl-large-brown-salted-meat",
        "Type": "Block",
        "StackSize": 1
    }],
    "IsTool": false,
    "CraftSound": "sounds/block/planks",
    "Disabled": false
 },
 {
    "Mode": "Swap",
    "Takes": {
		"Code": "game:food-bowl-large-fire-raw-meat",
        "Type": "Block",        
		"Remove": true	
    },
    "Tool": {
        "Code": "game:salt",
        "Type": "item",
		"StackSize": 32
    },
    "Makes": [{
        "Code": "game:food-bowl-large-fire-salted-meat",
        "Type": "Block",
        "StackSize": 1
    }],
    "IsTool": false,
    "CraftSound": "sounds/block/planks",
    "Disabled": false
 },
 {
    "Mode": "Swap",
    "Takes": {
		"Code": "game:food-bowl-large-red-raw-meat",
        "Type": "Block",        
		"Remove": true	
    },
    "Tool": {
        "Code": "game:salt",
        "Type": "item",
		"StackSize": 32
    },
    "Makes": [{
        "Code": "game:food-bowl-large-red-salted-meat",
        "Type": "Block",
        "StackSize": 1
    }],
    "IsTool": false,
    "CraftSound": "sounds/block/planks",
    "Disabled": false
 },
]